forpy/__init__.py
forpy/core.py
forpy/errors.py
for.py-1.0.4.dist-info/LICENSE
for.py-1.0.4.dist-info/METADATA
for.py-1.0.4.dist-info/WHEEL
for.py-1.0.4.dist-info/top_level.txt
for.py-1.0.4.dist-info/RECORD
