Metadata-Version: 2.1
Name: for.py
Version: 1.0.4
Summary: An async Python API wrapper for the Fortnite API
Home-page: https://github.com/Akhil2149/forpy
Author: Akhil
Author-email: akhilaug2003@gmail.com
License: MIT
Keywords: fortnite, forpy, api-wrapper, async
Platform: UNKNOWN
Requires-Python: >=3.6
Requires-Dist: aiohttp
Requires-Dist: python-box
